pyteslamate/__init__.py
pyteslamate/exceptions.py
pyteslamate/models.py
pyteslamate/py.typed
pyteslamate/pyteslamate.py
pyteslamate-0.1.0.dist-info/WHEEL
pyteslamate-0.1.0.dist-info/METADATA
pyteslamate-0.1.0.dist-info/RECORD
