Metadata-Version: 2.4
Name: pyteslamate
Version: 0.1.0
Summary: Asynchronous Python client for the Teslamate API
Keywords: python-teslamate,api,async,client
Author: Joel Pérez Izquierdo
Author-email: Joel Pérez Izquierdo <joelperez91@gmail.com>
License-Expression: MIT
Classifier: Framework :: AsyncIO
Classifier: Intended Audience :: Developers
Classifier: License :: OSI Approved :: MIT License
Classifier: Natural Language :: English
Classifier: Programming Language :: Python :: 3.11
Classifier: Programming Language :: Python :: 3.12
Classifier: Programming Language :: Python :: 3.13
Classifier: Programming Language :: Python :: 3.14
Classifier: Programming Language :: Python :: 3
Classifier: Topic :: Software Development :: Libraries :: Python Modules
Requires-Dist: aiohttp>=3.0.0
Requires-Dist: pydantic>=2.0.0
Requires-Python: >=3.11
